[
  {
    "name": "ax",
    "type": "chess",
    "result": "a wins by resignation",
    "moves": 0,
    "timestamp": "2025-05-27 03:20:35"
  },
  {
    "name": "ax",
    "type": "chess",
    "result": "x wins by resignation",
    "moves": 3,
    "timestamp": "2025-05-27 03:22:40"
  },
  {
    "name": "ax",
    "type": "checkers",
    "result": "x wins by resignation",
    "moves": 0,
    "timestamp": "2025-05-27 03:22:59"
  },
  {
    "name": "ax",
    "type": "checkers",
    "result": "x wins by resignation",
    "moves": 1,
    "timestamp": "2025-05-27 03:25:24"
  },
  {
    "name": "ax",
    "type": "chess",
    "result": "x wins by resignation",
    "moves": 6,
    "timestamp": "2025-05-27 03:25:59"
  },
  {
    "name": "ax",
    "type": "chess",
    "result": "AI Bot wins by resignation",
    "moves": 8,
    "timestamp": "2025-05-27 03:26:32"
  },
  {
    "name": "ax",
    "type": "chess",
    "result": "a wins by resignation",
    "moves": 1,
    "timestamp": "2025-05-27 03:26:53"
  },
  {
    "name": "AX",
    "type": "chess",
    "result": "X wins by resignation",
    "moves": 1,
    "timestamp": "2025-05-29 18:06:29"
  },
  {
    "name": "AX",
    "type": "chess",
    "result": "X wins by resignation",
    "moves": 2,
    "timestamp": "2025-05-31 23:42:08"
  },
  {
    "name": "AX",
    "type": "chess",
    "result": "X wins by resignation",
    "moves": 2,
    "timestamp": "2025-05-31 23:50:55"
  },
  {
    "name": "ax",
    "type": "chess",
    "result": "Draw",
    "moves": 0,
    "timestamp": "2025-05-31 23:51:10"
  },
  {
    "name": "AX",
    "type": "chess",
    "result": "X wins by resignation",
    "moves": 0,
    "timestamp": "2025-05-31 23:51:25"
  },
  {
    "name": "AX",
    "type": "chess",
    "result": "AI Bot wins by resignation",
    "moves": 4,
    "timestamp": "2025-05-31 23:53:36"
  },
  {
    "name": "AX",
    "type": "checkers",
    "result": "AI Bot wins by resignation",
    "moves": 1,
    "timestamp": "2025-06-01 00:05:53"
  },
  {
    "name": "AX",
    "type": "checkers",
    "result": "AI Bot wins by resignation",
    "moves": 1,
    "timestamp": "2025-06-01 00:08:40"
  },
  {
    "name": "AX",
    "type": "checkers",
    "result": "X wins by resignation",
    "moves": 0,
    "timestamp": "2025-06-01 00:15:20"
  },
  {
    "name": "AX",
    "type": "checkers",
    "result": "AI Bot wins by resignation",
    "moves": 0,
    "timestamp": "2025-06-01 15:20:07"
  },
  {
    "name": "AX",
    "type": "checkers",
    "result": "X wins by resignation",
    "moves": 0,
    "timestamp": "2025-06-01 15:20:31"
  },
  {
    "name": "AX",
    "type": "checkers",
    "result": "AI Bot wins by resignation",
    "moves": 0,
    "timestamp": "2025-06-01 15:20:51"
  },
  {
    "name": "AX",
    "type": "chess",
    "result": "A wins by resignation",
    "moves": 1,
    "timestamp": "2025-06-01 15:21:37"
  },
  {
    "name": "AX",
    "type": "checkers",
    "result": "A wins by resignation",
    "moves": 0,
    "timestamp": "2025-06-01 15:25:22"
  },
  {
    "name": "AX",
    "type": "checkers",
    "result": "AI Bot wins by resignation",
    "moves": 0,
    "timestamp": "2025-06-01 15:25:58"
  },
  {
    "name": "AX",
    "type": "chess",
    "result": "Draw",
    "moves": 2,
    "timestamp": "2025-06-01 15:26:31"
  },
  {
    "name": "AX",
    "type": "checkers",
    "result": "Draw",
    "moves": 0,
    "timestamp": "2025-06-01 15:32:05"
  },
  {
    "name": "AX",
    "type": "chess",
    "result": "A wins by resignation",
    "moves": 3,
    "timestamp": "2025-06-03 22:57:05"
  },
  {
    "name": "ax",
    "type": "checkers",
    "result": "a wins by resignation",
    "moves": 1,
    "timestamp": "2025-06-03 22:57:36"
  },
  {
    "name": "AX",
    "type": "chess",
    "result": "A wins by resignation",
    "moves": 5,
    "timestamp": "2025-06-03 23:06:52"
  },
  {
    "name": "AX",
    "type": "chess",
    "result": "A wins by resignation",
    "moves": 3,
    "timestamp": "2025-06-03 23:10:03"
  },
  {
    "name": "AX",
    "type": "chess",
    "result": "X wins by resignation",
    "moves": 0,
    "timestamp": "2025-06-09 13:44:52"
  },
  {
    "name": "ax",
    "type": "chess",
    "result": "a wins by resignation",
    "moves": 3,
    "timestamp": "2025-06-22 23:50:23"
  },
  {
    "name": "AX",
    "type": "chess",
    "result": "X wins by resignation",
    "moves": 8,
    "timestamp": "2025-06-22 23:52:56"
  },
  {
    "name": "AX",
    "type": "checkers",
    "result": "A wins by resignation",
    "moves": 1,
    "timestamp": "2025-06-22 23:53:24"
  }
]